gom/__api__.py
gom/__common__.py
gom/__config__.py
gom/__encoding__.py
gom/__init__.py
gom/__logging__.py
gom/__network__.py
gom/__state__.py
gom/__test__.py
gom/__tools__.py
gom/__types__.py
gom/api/__internal__progress/__init__.py
gom/api/addons/__init__.py
gom/api/dialog/__init__.py
gom/api/extensions/__init__.py
gom/api/extensions/actuals/__init__.py
gom/api/extensions/diagrams/__init__.py
gom/api/extensions/diagrams/matplotlib_tools.py
gom/api/extensions/inspections/__init__.py
gom/api/extensions/nominals/__init__.py
gom/api/extensions/sequence/__init__.py
gom/api/extensions/views/__init__.py
gom/api/imaging/__init__.py
gom/api/infoitem/__init__.py
gom/api/interpreter/__init__.py
gom/api/introspection/__init__.py
gom/api/progress/__init__.py
gom/api/project/__init__.py
gom/api/script_resources/__init__.py
gom/api/scripted_checks_util/__init__.py
gom/api/scriptedelements/__init__.py
gom/api/selection/__init__.py
gom/api/services/__init__.py
gom/api/settings/__init__.py
gom/api/testing/__init__.py
gom/api/tools/__init__.py
zeiss_inspect_api-2027.0.0.2328.dist-info/licenses/LICENSE
zeiss_inspect_api-2027.0.0.2328.dist-info/METADATA
zeiss_inspect_api-2027.0.0.2328.dist-info/WHEEL
zeiss_inspect_api-2027.0.0.2328.dist-info/top_level.txt
zeiss_inspect_api-2027.0.0.2328.dist-info/RECORD
