Metadata-Version: 2.4
Name: zeiss_inspect_api
Version: 2027.0.0.2328
Summary: ZEISS INSPECT API
Author-email: Carl Zeiss GOM Metrology GmbH <info.optical.metrology@zeiss.com>
Project-URL: Homepage, https://github.com/ZEISS/zeiss-inspect-api-wheel
Classifier: Programming Language :: Python :: 3
Classifier: Operating System :: OS Independent
Requires-Python: >=3.9
License-File: LICENSE
Requires-Dist: websocket-client
Dynamic: license-file
